odoo/addons/stock_release_channel_geoengine/README.rst
odoo/addons/stock_release_channel_geoengine/__init__.py
odoo/addons/stock_release_channel_geoengine/__manifest__.py
odoo/addons/stock_release_channel_geoengine/i18n/it.po
odoo/addons/stock_release_channel_geoengine/i18n/stock_release_channel_geoengine.pot
odoo/addons/stock_release_channel_geoengine/models/__init__.py
odoo/addons/stock_release_channel_geoengine/models/res_partner.py
odoo/addons/stock_release_channel_geoengine/models/stock_release_channel.py
odoo/addons/stock_release_channel_geoengine/readme/CONFIGURE.rst
odoo/addons/stock_release_channel_geoengine/readme/CONTRIBUTORS.rst
odoo/addons/stock_release_channel_geoengine/readme/DESCRIPTION.rst
odoo/addons/stock_release_channel_geoengine/readme/INSTALL.rst
odoo/addons/stock_release_channel_geoengine/static/description/icon.png
odoo/addons/stock_release_channel_geoengine/static/description/index.html
odoo/addons/stock_release_channel_geoengine/tests/__init__.py
odoo/addons/stock_release_channel_geoengine/tests/common.py
odoo/addons/stock_release_channel_geoengine/tests/test_stock_release_channel_geoengine.py
odoo/addons/stock_release_channel_geoengine/views/res_partner.xml
odoo/addons/stock_release_channel_geoengine/views/stock_release_channel.xml
odoo_addon_stock_release_channel_geoengine-16.0.2.0.0.1.dist-info/METADATA
odoo_addon_stock_release_channel_geoengine-16.0.2.0.0.1.dist-info/WHEEL
odoo_addon_stock_release_channel_geoengine-16.0.2.0.0.1.dist-info/top_level.txt
odoo_addon_stock_release_channel_geoengine-16.0.2.0.0.1.dist-info/RECORD
